setup.py
agoku/__init__.py
agoku/iapp.py
agoku/base/__init__.py
agoku/base/context.py
agoku/base/dependencys.py
agoku/base/gokuapp.py
agoku/base/middleware.py
agoku/libs/__init__.py
agoku/libs/decorators/__init__.py
agoku/libs/decorators/logs.py
agoku/libs/events/__init__.py
agoku/libs/events/base.py
agoku/libs/events/event_handler.py
agoku/libs/events/event_type.py
agoku/libs/task/__init__.py
agoku/libs/worker/__init__.py
agoku/libs/worker/woker.py
agoku/pulg/__init__.py
agoku/uitls/__init__.py
agoku/uitls/body_parse.py
agoku/uitls/singleton.py
agokufastapi.egg-info/PKG-INFO
agokufastapi.egg-info/SOURCES.txt
agokufastapi.egg-info/dependency_links.txt
agokufastapi.egg-info/requires.txt
agokufastapi.egg-info/top_level.txt
cremb/__init__.py
cremb/app.py
cremb/pulgs/__init__.py
cremb/pulgs/test_pulg/__init__.py